fastai_prims/__init__.py
fastai_prims/fastai_tl.py
fastai_prims-2022.3.25.dist-info/METADATA
fastai_prims-2022.3.25.dist-info/WHEEL
fastai_prims-2022.3.25.dist-info/entry_points.txt
fastai_prims-2022.3.25.dist-info/top_level.txt
fastai_prims-2022.3.25.dist-info/RECORD
