Metadata-Version: 2.1
Name: fastai-prims
Version: 2022.3.25
Summary: Fastai Image Processing primitives
Home-page: https://gitlab.com/datadrivendiscovery/fastai_prims
Author: TEAM
License: Apache-2.0
Platform: UNKNOWN
Requires-Dist: d3m
Requires-Dist: torch (==1.7.0)
Requires-Dist: torchvision (==0.8.1)
Requires-Dist: fastai (==2.3.0)
Requires-Dist: efficientnet-pytorch (==0.7.1)
